{"__type__":"cc.JsonAsset","_name":"config_02","json":{"tag":"管理学原理","type":"单选题","configArr":[{"title":"31.管理学形成的标志是","A":"韦伯的理想行政组织理论","B":"法约尔的管理过程理论","C":"梅奥的人际关系学说","D":"泰罗的科学管理理论","answer":"D"},{"title":"32.19世纪的工业革命与20世纪下半叶的计算机革命,对所有组织及其管理均产生了极大的影响,这属于组织环境中的哪一环境因素的作用?","A":"政治因素高率","B":"科技因素","C":"经济因素","D":"社会文化因素","answer":"B"},{"title":"33.与计划职能联系最紧密的管理职能是","A":"控制","B":"组织","C":"领导","D":"协调用","answer":"A"},{"title":"34.快乐食品公司以婴幼儿为目标顾客,专门从事婴幼儿食品的生产,并取得了良好的市场业绩,这种战略属于","A":"成本领先战略","B":"差异化战略","C":"集中化战略","D":"多元化战略","answer":"C"},{"title":"35.以过去为基础推测未来,以昨天为依据估算今后,这是","A":"决策","B":"规划","C":"程序","D":"预测","answer":"D"},{"title":"36.通过背对背地征询专家意见并多次反复的决策方法是","A":"因果法","B":"德尔菲法","C":"外推法","D":"边际分析法","answer":"B"},{"title":"37.职务、职责、职权三者如同一个等边三角形,这体现的是组织设计中的","A":"责权一致原理","B":"目标统一原理","C":"分工协作原理","D":"管理宽度原理","answer":"A"},{"title":"38.存在双重领导的组织结构类型是","A":"直线一参谋制","B":"直线制","C":"事业部制","D":"矩阵制","answer":"D"},{"title":"39.某跨国公司在世界多地设有销售机构,该公司部门划分的依据是","A":"职能","B":"产品","C":"地区","D":"人数","answer":"C"},{"title":"40.为了加强控制,阳光公司要求各部门在日常工作中必须随时向总经理请示汇报,这种做法属于","A":"集权化","B":"分权化","C":"部门化","D":"多元化","answer":"A"},{"title":"41.“质量水平对应百万机会缺陷数为3.4的目标”,这种观点对应的是","A":"业务过程管理","B":"系统管理","C":"六西格玛管理","D":"权变管理","answer":"C"},{"title":"42.旺旺超市根据管理者工作职位的相似性,将处于同一级别的管理者放到一个考核小组,按照事先规定的考评标准,采用两两比较的方式进行考评。这种做法属于","A":"考试法","B":"对比法","C":"成绩记录法","D":"自我考评法","answer":"B"},{"title":"43.对生产车间的班组长而言,其管理技能侧重于","A":"技术技能","B":"概念技能","C":"人事技能","D":"政治技能","answer":"A"},{"title":"44.在布莱克和穆登的管理方格理论中,如果管理者仅仅注重生产效率的提高,极少关心人,极其独断专行,则这种管理方式是","A":"贫乏型管理","B":"独裁的、重任务型的管理","C":"战斗集体型管理","D":"乡村俱乐部型管理","answer":"B"},{"title":"45.天天软件公司的程序员分布在全球各地,一些成员之间通过电子邮件、视频会议等手段开展远程工作,形成了团队作业小组。这种团队是","A":"自我管理团队","B":"协同工作团队","C":"虚拟团队","D":"学习型团队","answer":"C"},{"title":"46.当团队已经成熟为一个具有高度凝聚力的整体,团队成员对他人的优缺点以及他们如何支持使命了如指掌,并能够解决群体问题时,团队处于","A":"形成阶段","B":"震荡阶段","C":"规范阶段","D":"执行阶段","answer":"D"},{"title":"47.通过命令方式传达上级的政策、计划、规定等信息的沟通方式是","A":"上向沟通","B":"下向沟通","C":"横向沟通","D":"斜向沟通","answer":"B"},{"title":"48.小李在工作中积极认真,但主管领导总是视而不见,没有给予其及时的认可和鼓励。时间一长,小李的工作积极性消磨殆尽。这属于强化理论的","A":"积极强化","B":"消极强化","C":"消失","D":"惩罚","answer":"C"},{"title":"49.“治病不如防病,防病不如讲卫生。”这种说法类同于管理中的哪一种控制类型?","A":"现场控制","B":"全面控制","C":"反馈控制","D":"前馈控制","answer":"D"},{"title":"50.通过财务、顾客、内部过程、学习和成长等方面综合考察管理绩效,这种控制方法是","A":"平衡计分卡","B":"计划评审技术","C":"预算","D":"管理审核","answer":"A"},{"title":"51.管理的核心是处理好","A":"人与物的关系","B":"财与物的关系","C":"物与物的关系","D":"人际关系","answer":"D"},{"title":"52.人口密度、年龄结构属于下列哪种宏观环境因素?","A":"社会文化环境","B":"政治法律环境","C":"经济环境","D":"科技环境","answer":"A"},{"title":"53.一般而言,长期计划往往是","A":"战术性计划","B":"战略性计划","C":"年度计划","D":"作业计划","answer":"B"},{"title":"54.甲玩具公司通过市场调查和分析,发现某种儿童玩具具有广阔的发展前景,而公司又有能力研发和生产该产品,决定进军该市场。这体现了计划工作的哪一步?","A":"估量机会","B":"确定目标","C":"选择方案","D":"确定前提条件","answer":"A"},{"title":"55.随着数码相机的广泛应用,某胶卷生产企业及时调整生产结构,压缩生产规模,逐渐从胶卷市场撤离。该做法属于","A":"内部增长战略","B":"多元化战略","C":"收缩战略","D":"稳定战略","answer":"C"},{"title":"56.对程序化决策描述正确的是","A":"重复出现的、例行性决策","B":"非重复性的、例外决策","C":"非重复性的、例行性决策","D":"重复出现的、例外决策","answer":"A"},{"title":"57.通过对追加的支出与收入进行对比分析的决策方法是","A":"期望值法","B":"效用法","C":"概率法","D":"边际分析法","answer":"D"},{"title":"58.部门划分主要解决组织设计中的","A":"目标确立","B":"纵向设计","C":"横向设计","D":"层次划分","answer":"C"},{"title":"59.分权有助于","A":"提高下级的积极性","B":"提高上级命令的执行效率","C":"增加管理的层次","D":"加强领导的控制力","answer":"A"},{"title":"60.以下不属于人员配备原理的是","A":"责权利一致原理","B":"公开竞争原理","C":"用人之长原理","D":"因人设岗原理","answer":"D"}]}}